exo/__init__.py
exo/calculate_contrast_threshold.py
exo/cli.py
exo/create_fourcolor_plot.py
exo/format_peaks.py
exo/make_composite.py
exo/make_heatmap.py
exo/make_motif_composite.py
exo/merge_heatmap_png.py
exo/process_genome_coverage.py
exo/remove_overlapping_motifs.py
exo/total_tag_ordering.py
exo-0.1.2.dist-info/LICENSE
exo-0.1.2.dist-info/METADATA
exo-0.1.2.dist-info/WHEEL
exo-0.1.2.dist-info/entry_points.txt
exo-0.1.2.dist-info/top_level.txt
exo-0.1.2.dist-info/RECORD
