Metadata-Version: 2.1
Name: exo
Version: 0.1.2
Summary: Quality Control and Visualization utilities for Yeast Epigenome Project 
Home-page: https://github.com/CEGRcode/exo
Author: Prashant Kumar Kuntala
Author-email: prashantkuntala@gmail.com
License: MIT license
Keywords: exo
Platform: UNKNOWN
Classifier: Development Status :: 3 - Alpha
Classifier: Intended Audience :: Developers
Classifier: License :: OSI Approved :: MIT License
Classifier: Natural Language :: English
Classifier: Topic :: Utilities
Classifier: Programming Language :: Python
Classifier: Programming Language :: Python :: 2.7
Classifier: Programming Language :: Python :: 3.7
Requires-Dist: Click (>=7.0)
Requires-Dist: matplotlib
Requires-Dist: numpy
Requires-Dist: pyfiglet
Requires-Dist: pandas
Requires-Dist: pillow
